nireports/__init__.py
nireports/_version.py
nireports/conftest.py
nireports/py.typed
nireports/_vendored/__init__.py
nireports/_vendored/LICENSES/LICENSE.svgutils.txt
nireports/_vendored/svgutils/__init__.py
nireports/_vendored/svgutils/common.py
nireports/_vendored/svgutils/compose.py
nireports/_vendored/svgutils/templates.py
nireports/_vendored/svgutils/transform.py
nireports/assembler/__init__.py
nireports/assembler/export.py
nireports/assembler/misc.py
nireports/assembler/pyodide.py
nireports/assembler/report.py
nireports/assembler/reportlet.py
nireports/assembler/tools.py
nireports/assembler/data/__init__.py
nireports/assembler/data/default.yml
nireports/assembler/data/nipreps.json
nireports/assembler/data/report.tpl
nireports/assembler/data/rating-widget/bootstrap.yml
nireports/assembler/data/rating-widget/footer.tpl
nireports/assembler/data/rating-widget/header.tpl
nireports/assembler/data/rating-widget/navbar.tpl
nireports/assembler/tests/test_report.py
nireports/cli/__init__.py
nireports/interfaces/__init__.py
nireports/interfaces/base.py
nireports/interfaces/dmri.py
nireports/interfaces/fmri.py
nireports/interfaces/mosaic.py
nireports/interfaces/nuisance.py
nireports/interfaces/reporting/__init__.py
nireports/interfaces/reporting/base.py
nireports/interfaces/reporting/masks.py
nireports/interfaces/reporting/registration.py
nireports/interfaces/reporting/segmentation.py
nireports/reportlets/__init__.py
nireports/reportlets/mosaic.py
nireports/reportlets/notebook.py
nireports/reportlets/nuisance.py
nireports/reportlets/surface.py
nireports/reportlets/utils.py
nireports/reportlets/xca.py
nireports/reportlets/modality/__init__.py
nireports/reportlets/modality/dwi.py
nireports/reportlets/modality/func.py
nireports/tests/__init__.py
nireports/tests/conftest.py
nireports/tests/test_dwi.py
nireports/tests/test_interfaces.py
nireports/tests/test_interfaces_registration.py
nireports/tests/test_interfaces_segmentation.py
nireports/tests/test_interfaces_utils.py
nireports-25.3.0.dist-info/METADATA
nireports-25.3.0.dist-info/WHEEL
nireports-25.3.0.dist-info/licenses/LICENSE
nireports-25.3.0.dist-info/RECORD
