Metadata-Version: 2.4
Name: nireports
Version: 25.3.0
Summary: NiReports - The Visual Report System (VRS) of NiPreps
Project-URL: Homepage, https://github.com/nipreps/nireports
Project-URL: NiPreps, https://www.nipreps.org/
Author-email: The NiPreps Developers <nipreps@gmail.com>
License-Expression: Apache-2.0
License-File: LICENSE
Classifier: Development Status :: 4 - Beta
Classifier: Intended Audience :: Science/Research
Classifier: License :: OSI Approved :: Apache Software License
Classifier: Programming Language :: Python :: 3.10
Classifier: Programming Language :: Python :: 3.11
Classifier: Programming Language :: Python :: 3.12
Classifier: Programming Language :: Python :: 3.13
Classifier: Topic :: Scientific/Engineering :: Image Recognition
Requires-Python: >=3.10
Requires-Dist: acres>=0.2
Requires-Dist: lxml>=4.7
Requires-Dist: matplotlib>=3.6
Requires-Dist: nibabel>=5.0
Requires-Dist: nilearn>=0.10.1
Requires-Dist: nipype>=1.8.5
Requires-Dist: numpy>=1.24
Requires-Dist: pandas>=1.5
Requires-Dist: pybids>=0.15.1
Requires-Dist: pyyaml>=6.0
Requires-Dist: seaborn>=0.13
Requires-Dist: templateflow>=23.1
Provides-Extra: all
Requires-Dist: coverage[toml]>=7.10; extra == 'all'
Requires-Dist: furo; extra == 'all'
Requires-Dist: packaging>=25.0; extra == 'all'
Requires-Dist: pre-commit; extra == 'all'
Requires-Dist: pydot>=1.2.3; extra == 'all'
Requires-Dist: pydotplus; extra == 'all'
Requires-Dist: pytest-cov>=6.2; extra == 'all'
Requires-Dist: pytest-env>=1.1; extra == 'all'
Requires-Dist: pytest-xdist>=3.7; extra == 'all'
Requires-Dist: pytest>=8.4; extra == 'all'
Requires-Dist: ruff; extra == 'all'
Requires-Dist: sphinx; extra == 'all'
Requires-Dist: sphinx>=8.0; extra == 'all'
Requires-Dist: sphinxcontrib-apidoc; extra == 'all'
Requires-Dist: sphinxcontrib-napoleon; extra == 'all'
Provides-Extra: dev
Requires-Dist: pre-commit; extra == 'dev'
Requires-Dist: ruff; extra == 'dev'
Provides-Extra: doc
Requires-Dist: furo; extra == 'doc'
Requires-Dist: pydot>=1.2.3; extra == 'doc'
Requires-Dist: pydotplus; extra == 'doc'
Requires-Dist: sphinx; extra == 'doc'
Requires-Dist: sphinxcontrib-apidoc; extra == 'doc'
Requires-Dist: sphinxcontrib-napoleon; extra == 'doc'
Provides-Extra: docs
Requires-Dist: furo; extra == 'docs'
Requires-Dist: pydot>=1.2.3; extra == 'docs'
Requires-Dist: pydotplus; extra == 'docs'
Requires-Dist: sphinx; extra == 'docs'
Requires-Dist: sphinxcontrib-apidoc; extra == 'docs'
Requires-Dist: sphinxcontrib-napoleon; extra == 'docs'
Provides-Extra: test
Requires-Dist: coverage[toml]>=7.10; extra == 'test'
Requires-Dist: packaging>=25.0; extra == 'test'
Requires-Dist: pytest-cov>=6.2; extra == 'test'
Requires-Dist: pytest-env>=1.1; extra == 'test'
Requires-Dist: pytest-xdist>=3.7; extra == 'test'
Requires-Dist: pytest>=8.4; extra == 'test'
Requires-Dist: sphinx>=8.0; extra == 'test'
Provides-Extra: tests
Requires-Dist: coverage[toml]>=7.10; extra == 'tests'
Requires-Dist: packaging>=25.0; extra == 'tests'
Requires-Dist: pytest-cov>=6.2; extra == 'tests'
Requires-Dist: pytest-env>=1.1; extra == 'tests'
Requires-Dist: pytest-xdist>=3.7; extra == 'tests'
Requires-Dist: pytest>=8.4; extra == 'tests'
Requires-Dist: sphinx>=8.0; extra == 'tests'
Provides-Extra: types
Requires-Dist: lxml-stubs; extra == 'types'
Requires-Dist: pandas-stubs; extra == 'types'
Requires-Dist: pytest; extra == 'types'
Requires-Dist: scipy-stubs; extra == 'types'
Requires-Dist: types-jinja2; extra == 'types'
Requires-Dist: types-pyyaml; extra == 'types'
